inFairness/__init__.py
inFairness/auditor/__init__.py
inFairness/auditor/auditor.py
inFairness/auditor/datainterface.py
inFairness/auditor/sensei_auditor.py
inFairness/auditor/sensr_auditor.py
inFairness/auditor/senstir_auditor.py
inFairness/distances/__init__.py
inFairness/distances/distance.py
inFairness/distances/euclidean_dists.py
inFairness/distances/explore_distance.py
inFairness/distances/logistic_sensitive_subspace.py
inFairness/distances/mahalanobis_distance.py
inFairness/distances/sensitive_subspace_dist.py
inFairness/distances/wasserstein_distance.py
inFairness/fairalgo/__init__.py
inFairness/fairalgo/datainterfaces.py
inFairness/fairalgo/sensei.py
inFairness/fairalgo/sensr.py
inFairness/fairalgo/senstir.py
inFairness/postprocessing/__init__.py
inFairness/postprocessing/base_postprocessing.py
inFairness/postprocessing/data_ds.py
inFairness/postprocessing/datainterfaces.py
inFairness/postprocessing/distance_ds.py
inFairness/postprocessing/glif.py
inFairness/utils/__init__.py
inFairness/utils/datautils.py
inFairness/utils/misc.py
inFairness/utils/ndcg.py
inFairness/utils/params.py
inFairness/utils/plackett_luce.py
inFairness/utils/postprocessing.py
inFairness/utils/validationutils.py
inFairness-0.2.3.dist-info/LICENSE
inFairness-0.2.3.dist-info/METADATA
inFairness-0.2.3.dist-info/WHEEL
inFairness-0.2.3.dist-info/top_level.txt
inFairness-0.2.3.dist-info/RECORD
