Metadata-Version: 2.1
Name: inFairness
Version: 0.2.3
Summary: inFairness is a Python package to train and audit individually fair PyTorch models
Home-page: https://github.com/IBM/inFairness
Author: IBM Research
Author-email: mayank.agarwal@ibm.com, aldo.pareja@ibm.com, onkarbhardwaj@ibm.com, mikhail.yurochkin@ibm.com
Keywords: individual fairness,ai fairness,trustworthy ai,machine learning
Requires-Python: >=3.7
License-File: LICENSE
Requires-Dist: numpy (>=1.21.6)
Requires-Dist: pandas (>=1.3.5)
Requires-Dist: POT (>=0.8.0)
Requires-Dist: scikit-learn (>=0.24.2)
Requires-Dist: scipy (>=1.5.4)
Requires-Dist: torch (>=1.13.0)
